synchronicity/__init__.py
synchronicity/annotations.py
synchronicity/async_utils.py
synchronicity/async_wrap.py
synchronicity/callback.py
synchronicity/combined_types.py
synchronicity/exceptions.py
synchronicity/interface.py
synchronicity/overload_tracking.py
synchronicity/py.typed
synchronicity/synchronizer.py
synchronicity/type_stubs.py
synchronicity-0.10.1.dist-info/METADATA
synchronicity-0.10.1.dist-info/WHEEL
synchronicity-0.10.1.dist-info/licenses/LICENSE
synchronicity-0.10.1.dist-info/RECORD
